fluoscenepy/__init__.py
fluoscenepy/fluoscene.py
fluoscenepy/tests/__init__.py
fluoscenepy/tests/test_fluoscene.py
fluoscenepy/utils/__init__.py
fluoscenepy/utils/acc_comp_funcs.py
fluoscenepy/utils/comp_funcs.py
fluoscenepy/utils/compiled_objects_gen.py
fluoscenepy/utils/raw_objects_gen.py
fluoscenepy-0.0.5.dist-info/licenses/LICENSE
fluoscenepy-0.0.5.dist-info/METADATA
fluoscenepy-0.0.5.dist-info/WHEEL
fluoscenepy-0.0.5.dist-info/top_level.txt
fluoscenepy-0.0.5.dist-info/RECORD
