Metadata-Version: 2.4
Name: fluoscenepy
Version: 0.0.5
Summary: Simulation of a microscopic image with round (beads) and elongated fluorescent objects
Author: Sergei Klykov
Author-email: sergej.klykow@gmail.com
Project-URL: Homepage, https://sklykov.github.io/fluoscenepy/
Project-URL: Repository, https://github.com/sklykov/fluoscenepy/
Project-URL: Bug Tracker, https://github.com/sklykov/fluoscenepy/issues/
Project-URL: Documentation, https://sklykov.github.io/fluoscenepy/api_doc/fluoscenepy/fluoscene.html
Project-URL: Changelog, https://github.com/sklykov/fluoscenepy/blob/main/CHANGELOG.md
Keywords: fluorescent-microscopic-image-simulation
Classifier: Programming Language :: Python :: 3
Classifier: Operating System :: OS Independent
Requires-Python: >=3.8
License-File: LICENSE
Requires-Dist: numpy
Requires-Dist: matplotlib
Dynamic: license-file
